neftpy/__init__.py
neftpy/curves.py
neftpy/fluid.py
neftpy/uconst.py
neftpy/uconvert.py
neftpy/upvt_gas.py
neftpy/upvt_np_vect.py
neftpy/upvt_oil.py
neftpy/upvt_wat.py
neftpy/ureservoir.py
neftpy-0.2.dist-info/METADATA
neftpy-0.2.dist-info/WHEEL
neftpy-0.2.dist-info/licenses/LICENSE
neftpy-0.2.dist-info/RECORD
