Metadata-Version: 2.3
Name: neftpy
Version: 0.2
Summary: Petroluem production engineering calculations package. Inspired by Unifloc VBA.
Project-URL: Homepage, https://github.com/unifloc/neftpy
Project-URL: Issues, https://github.com/unifloc/neftpy/issues
Author-email: khabibullin Rinat <khabibullinra@gmail.com>
License-File: LICENSE
Classifier: License :: OSI Approved :: BSD License
Classifier: Operating System :: OS Independent
Classifier: Programming Language :: Python :: 3
Requires-Python: >=3.10
